{
    "categories": [
        {
            "name": "Netflix",
            "icon": "netflix.png",
            "items": [
                
                {
                    "name": "Netflix 1p1u 1Minggu",
                    "description": "4K UHD, Hanya boleh login satu device, Bisa Limit",
                    "price": "Rp 15,000"
                },
                {
                    "name": "Netflix 1p1u 1Bulan",
                    "description": "4K UHD, Hanya boleh login satu device, Bisa Limit",
                    "price": "Rp 34,000"
                },
                {
                    "name": "Netflix Private 1 Bulan",
                    "description": "4K UHD, Private 1B, Login 5-10 Device",
                    "price": "Rp 140,000"
                }
            ]
        },
        {
            "name": "Viu",
            "icon": "viu.png",
            "items": [
                {
                    "name": "Viu Premium 1 Bulan",
                    "description": "No ads, HD quality, Login 1 Device",
                    "price": "Rp 7,000"
                },
                {
                    "name": "Viu Premium 6 Bulan",
                    "description": "No ads, HD quality, Login 1 Device",
                    "price": "Rp 20,000"
                }
            ]
        },
        {
            "name": "Loklok",
            "icon": "loklok.png",
            "items": [
                {
                    "name": "Loklok VIP 1 Bulan",
                    "description": "Full access, Login 1 Device",
                    "price": "Rp 15,000"
                }
            ]
        },
        {
            "name": "Canva",
            "icon": "canva.png",
            "items": [
                {
                    "name": "Canva Pro 1 Bulan",
                    "description": "Full access to Pro features",
                    "price": "Rp 5,000"
                },
                {
                    "name": "Canva Pro 1 Tahun",
                    "description": "Full access to Pro features",
                    "price": "Rp 25,000"
                }
            ]
        },
        {
            "name": "Mobile Legends",
            "icon": "mobilelegends.png",
            "items": [
                {
                    "name": "86 Diamonds",
                    "description": "Mobile Legends",
                    "price": "Rp 20,000"
                }
            ]
        },
        {
            "name": "Free Fire",
            "icon": "ff.png",
            "items": [
                {
                    "name": "70 Diamonds",
                    "description": "Free Fire",
                    "price": "Rp 10,000"
                }
            ]
        }
    ]
}
